dcma/__init__.py
dcma/__main__.py
dcma/core.py
dcma/_src/__init__.py
dcma/_src/_core_methods.py
dcma/_src/conv/__init__.py
dcma/_src/conv/export_dfs.py
dcma/_src/helpers/__init__.py
dcma/_src/helpers/auxfunc.py
dcma/data/codons.csv
dcma/data/pols.csv
dcma-0.1.2.dist-info/LICENSE
dcma-0.1.2.dist-info/METADATA
dcma-0.1.2.dist-info/WHEEL
dcma-0.1.2.dist-info/entry_points.txt
dcma-0.1.2.dist-info/top_level.txt
dcma-0.1.2.dist-info/RECORD
