Metadata-Version: 2.1
Name: dcma
Version: 0.1.2
Summary: Deep Codon Mutation Analyser
Home-page: https://github.com/janjusti/dcma
Author: Jan Justi
Author-email: jan.ma.justi@gmail.com
License: MIT
Platform: UNKNOWN
Classifier: Programming Language :: Python
Classifier: Programming Language :: Python :: 3.6
Requires-Dist: tqdm (>=4.31.1)
Requires-Dist: anytree (>=2.6.0)
Requires-Dist: pandas (>=0.24.2)
Requires-Dist: biopython (>=1.73)
Requires-Dist: openpyxl (>=2.6.2)
Requires-Dist: styleframe (>=2.0.3)
